probing-0.2.1.data/scripts/probing
probing-0.2.1.data/scripts/libprobing.so
probing/inspect/torch.py
probing/inspect/trace.py
probing/inspect/__init__.py
probing/tracing.py
probing/ext/example.py
probing/ext/torch.py
probing/ext/__init__.py
probing/testing/__init__.py
probing/repl/stack_magic.py
probing/repl/debug_magic.py
probing/repl/query_magic.py
probing/repl/torch_magic.py
probing/repl/inspect_magic.py
probing/repl/__init__.py
probing/repl/help_magic.py
probing/hooks/import_hook.py
probing/hooks/__init__.py
probing/core/engine.py
probing/core/__init__.py
probing/core/table.py
probing/profiling/torch_probe.py
probing/profiling/types.py
probing/profiling/collective/coll.py
probing/profiling/collective/__init__.py
probing/profiling/torch/module_utils.py
probing/profiling/torch/step.py
probing/profiling/torch/__init__.py
probing/profiling/__init__.py
probing/__init__.py
probing_hook.py
probing.pth
probing-0.2.1.dist-info/METADATA
probing-0.2.1.dist-info/WHEEL
probing-0.2.1.dist-info/RECORD
