Metadata-Version: 2.1
Name: probing
Version: 0.2.1
Summary: Performance and Stability Diagnostic Tool for AI Applications
License: Apache-2.0
Classifier: Programming Language :: Python :: 3
Classifier: Operating System :: POSIX :: Linux
Project-URL: Homepage, https://github.com/reiase/probing
Project-URL: Repository, https://github.com/reiase/probing
Keywords: debug, performance, python
Author: reiase <reiase@gmail.com>
Requires-Python: >=3.7
